parsel/__init__.py
parsel/csstranslator.py
parsel/py.typed
parsel/selector.py
parsel/utils.py
parsel/xpathfuncs.py
parsel_qpython-1.9.1.2.dist-info/METADATA
parsel_qpython-1.9.1.2.dist-info/WHEEL
parsel_qpython-1.9.1.2.dist-info/top_level.txt
parsel_qpython-1.9.1.2.dist-info/RECORD
