Metadata-Version: 2.4
Name: parsel-qpython
Version: 1.9.1.2
Summary: Parsel is a library to extract data from HTML and XML using XPath and CSS selectors
Author-email: The QPYPI Team <qpypi@qpython.org>
License: MIT AND (Apache-2.0 OR BSD-2-Clause)
Project-URL: Homepage, https://qpypi.qpython.org/project/parsel-qpython/
Classifier: Intended Audience :: Developers
Classifier: Intended Audience :: Education
Classifier: Intended Audience :: Information Technology
Classifier: Intended Audience :: End Users/Desktop
Classifier: License :: OSI Approved :: Apache Software License
Classifier: Operating System :: Android
Classifier: Programming Language :: Python
Classifier: Programming Language :: Python :: 3.12
Classifier: Topic :: Software Development
Requires-Python: ==3.12.*
Requires-Dist: cssselect>=1.2.0
Requires-Dist: jmespath
Requires-Dist: lxml-qpython
Requires-Dist: packaging
Requires-Dist: w3lib>=1.19.0
